{
  "entity_type": "Organism",
  "camouflage_presence": "Camouflage",
  "object_category": "Arachnid",
  "object_name": "Spider",
  "background_description": "The background consists of textured tree bark, primarily in shades of light gray, brown, and dark, shadowed areas. Some parts of the bark are covered with dark green moss or algae, especially in the deeper crevices. The overall texture is rough, irregular, and furrowed, with distinct cracks and folds. Vibrant green fern-like leaves are visible in the foreground and bottom edges.",
  "color_similarity": "high",
  "texture_similarity": "high",
  "contrast_difference": "low",
  "camouflage_score": 0.85,
  "confidence": 0.95,
  "camouflage_type": "Color blending",
  "explanation": "The spider exhibits strong camouflage by positioning itself within a deep, dark crevice of the tree bark. Its dark grayish-brown coloration, along with subtle patterns and hairy texture, closely matches the shadowed, dark, and moss-covered sections of the bark. The irregular body shape and leg positioning further help it blend with the rough contours and textures of the wood. The low contrast between the spider and its immediate surroundings, coupled with its excellent color and texture matching, makes it very difficult to spot at first glance."
}