{
  "entity_type": "Organism",
  "camouflage_presence": "Camouflage",
  "object_category": "Fish",
  "object_name": "Pipefish",
  "background_description": "The background consists of a shallow underwater environment characterized by a mix of green-blue algae and feathery, yellowish-brown aquatic vegetation. The seafloor visible towards the bottom left shows fragments of shells and sediment. The water appears slightly turbid with suspended particles, creating a mottled and textured overall environment.",
  "color_similarity": "high",
  "texture_similarity": "medium",
  "contrast_difference": "low",
  "camouflage_score": 0.85,
  "confidence": 0.95,
  "camouflage_type": "Color blending / Pattern matching / Shape disruption",
  "explanation": "The Pipefish exhibits excellent camouflage in this image. Its elongated, slender body and mottled coloration, featuring shades of brown, green-grey, and white speckles, blend seamlessly with the surrounding aquatic vegetation. The color palette of the pipefish closely matches the varied hues of the green algae and yellowish-brown feathery plant matter. The subtle texture and speckling on its body help it to mimic the irregular surfaces and fragmented nature of the background. Its linear shape further aids in disrupting its outline, making it difficult to distinguish from the linear strands of seaweed and detritus. The low contrast difference between the organism and its immediate environment means it does not visually 'pop out', but rather integrates into the visual clutter of the underwater scene, making it very hard for a predator or observer to spot."
}