{
  "entity_type": "Organism",
  "camouflage_presence": "No Camouflage",
  "object_category": "Environment",
  "object_name": "Underwater coral reef",
  "background_description": "The background consists of dark, textured rocky substrate covered with various types of coral and algae. Prominent features include clusters of branching corals with numerous small white-tipped polyps, and a large, pale blue-green ruffled soft coral in the upper-left. The overall scene is submerged in murky blue water.",
  "color_similarity": "none",
  "texture_similarity": "none",
  "contrast_difference": "medium",
  "camouflage_score": 0.0,
  "confidence": 0.9,
  "camouflage_type": "None",
  "explanation": "The image primarily showcases a vibrant underwater coral reef. While corals are marine organisms, their appearance here is characteristic of their natural growth forms and colors within their ecosystem. No specific organism in the image demonstrates active camouflage, such as color blending, disruptive patterns, or mimicry, to conceal itself from predators or prey. For example, the large ruffled coral, despite being an organism, presents a distinct shape and lighter blue-green coloration that stands out against the darker, more muted background, indicating a lack of intentional blending. The other corals with white-tipped polyps also have clear forms that are easily discernible within the scene. Given the lack of a specific 'invertebrate' category for 'object_category' in the schema, and the presence of numerous organisms forming a habitat, 'Environment' is chosen to reflect the overall context of the scene, even though 'entity_type' is 'Organism' due to the presence of animals (corals)."
}