{
  "entity_type": "Organism",
  "camouflage_presence": "Camouflage",
  "object_category": "Fish",
  "object_name": "GhostPipefish",
  "background_description": "The background consists of a dense, intricate structure of a crinoid (feather star) or similar sessile invertebrate. It features numerous branching arms covered in delicate, feathery pinnules, predominantly off-white or pale cream with regular brown or dark reddish-brown banding or segments. The overall texture is highly complex, feathery, and spiky, with darker, blurry areas suggesting depth.",
  "color_similarity": "high",
  "texture_similarity": "high",
  "contrast_difference": "low",
  "camouflage_score": "0.95",
  "confidence": "1.0",
  "camouflage_type": "Mimicry",
  "explanation": "The GhostPipefish exhibits exceptional camouflage, primarily through mimicry of its host crinoid. Its body is adorned with numerous filamentous and spiky dermal appendages that precisely replicate the texture and branching structure of the surrounding feathery pinnules of the crinoid. The fish's coloration, a mosaic of pale white/cream with reddish-brown and purplish reticulated patterns, perfectly matches the white and brown segments of the crinoid. This combination of physical resemblance and color/pattern matching effectively breaks up the fish's outline, making it incredibly difficult to distinguish from the environment. It appears to be an integral part of the crinoid itself, providing excellent concealment from predators."
}