{
  "entity_type": "Organism",
  "camouflage_presence": "No Camouflage",
  "object_category": "Bird",
  "object_name": "European Robin",
  "background_description": "The background consists of a light grey, smooth metal railing in the foreground, where the bird is perched. Behind the railing, there is a blurred, dark grey, and textured concrete or stone surface with hints of a deeper dark area directly behind the railing, and a lighter, mottled grey-brown surface above it, possibly showing some sparse green moss or lichen.",
  "color_similarity": "low",
  "texture_similarity": "low",
  "contrast_difference": "high",
  "camouflage_score": 0.0,
  "confidence": 1.0,
  "camouflage_type": "None",
  "explanation": "The European Robin in the image is not camouflaged. Its bright orange-red breast and face, along with its white belly, create a strong and high contrast against the neutral, mostly grey and dark brown background of the metal railing and the concrete wall. The bird is clearly distinguishable and stands out, making it easily visible. Its coloration is more for display than for blending into this specific environment."
}