{
  "entity_type": "Organism",
  "camouflage_presence": "Camouflage",
  "object_category": "Amphibian",
  "object_name": "Toad",
  "background_description": "The background consists of shallow, clear water with prominent ripples and reflections on the surface. Beneath the water, there is a dense layer of fallen autumn leaves in various stages of decay, ranging in color from reddish-brown to dark brown and tan, interspersed with dark sediment and small stones. A thin stick or branch is visible in the upper portion of the water. The overall environment is a stream bed or shallow pond floor with organic debris.",
  "color_similarity": "high",
  "texture_similarity": "high",
  "contrast_difference": "low",
  "camouflage_score": 0.85,
  "confidence": 0.95,
  "camouflage_type": "Color blending",
  "explanation": "The toad in the image exhibits strong camouflage through a combination of color blending and pattern matching. Its mottled brown and grayish skin perfectly matches the varied hues of the submerged wet leaves and dark sediment beneath the water. The rough, bumpy texture of the toad's skin also closely resembles the irregular and decaying textures of the fallen leaves. The ripples and reflections on the water's surface further enhance the camouflage by creating a dynamic, dappled light and shadow effect that breaks up the toad's outline and reduces overall contrast, making it extremely difficult to distinguish from its natural environment."
}