{
  "entity_type": "Organism",
  "camouflage_presence": "Camouflage",
  "object_category": "Mammal",
  "object_name": "Fox kits",
  "background_description": "The background consists mainly of vibrant green, somewhat overgrown grass with varying lengths and shades, along with some darker soil or shadowed areas visible beneath the blades. A few lighter green plant leaves are also visible on the right side.",
  "color_similarity": "low",
  "texture_similarity": "low",
  "contrast_difference": "medium",
  "camouflage_score": 0.4,
  "confidence": 0.95,
  "camouflage_type": "Color blending",
  "explanation": "The fox kits exhibit natural camouflage through 'Color blending'. Their reddish-brown and darker fur tones are inherently adapted to blend with forest floors, dry grass, and soil prevalent in their natural habitats. While the vibrant green grass in this specific image provides some contrast, their fur color offers a degree of blending with the less vibrant or darker earthy patches and shadows within the environment. However, their playful activity and the bright lighting make them easily detectable despite this inherent coloration."
}