{
  "entity_type": "Organism",
  "camouflage_presence": "Camouflage",
  "object_category": "Bird",
  "object_name": "Bittern",
  "background_description": "The background consists of a vast expanse of moorland or heathland. In the foreground and mid-ground, there is dense, low-lying vegetation, primarily dry heather and similar plants, characterized by reddish-brown, earthy tones, interspersed with lighter, straw-colored patches and hints of dark green foliage. The textures are fine, twiggy, and somewhat chaotic due to the dense growth. The distant background is a blurry, soft blue-grey, indicating a hazy horizon or distant hills.",
  "color_similarity": "high",
  "texture_similarity": "high",
  "contrast_difference": "low",
  "camouflage_score": "0.85",
  "confidence": "0.98",
  "camouflage_type": "Color blending / Pattern matching",
  "explanation": "The Bittern exhibits excellent camouflage in this image. Its plumage is a rich reddish-brown, intricately mottled with darker browns and lighter cream or pale brown flecks. This coloration and patterning almost perfectly match the dominant reddish-brown and straw-colored tones of the dry heather and dense vegetation in its immediate surroundings. The fine, dappled texture of its feathers also closely resembles the visual texture of the dense, twiggy plant growth. This combination of high color similarity and effective pattern matching results in a very low contrast difference between the bird and its environment, making it blend seamlessly with the moorland habitat. The bird's form is subtly disrupted by its patterning, further aiding its concealment among the visually noisy background."
}