{
  "entity_type": "Organism",
  "camouflage_presence": "Camouflage",
  "object_category": "Fish",
  "object_name": "GhostPipefish",
  "background_description": "The background consists of a gorgonian sea fan coral, characterized by vibrant orange, branched structures that form an intricate network. Numerous small, white, star-shaped polyps are extended along these orange branches, creating a textured, frilly appearance. Dark, shadowed areas are visible between the coral branches.",
  "color_similarity": "high",
  "texture_similarity": "high",
  "contrast_difference": "low",
  "camouflage_score": "0.9",
  "confidence": "1.0",
  "camouflage_type": "Mimicry",
  "explanation": "The GhostPipefish exhibits exceptional camouflage through a combination of color blending, pattern matching, and mimicry. Its body coloration, featuring a mottled pattern of orange, white, and reddish-brown, perfectly matches the hues of the gorgonian coral's orange branches and white polyps. The intricate, frilly, and spiky appendages extending from its body closely mimic the texture and morphology of the coral polyps and branches, effectively disrupting its outline and making it blend seamlessly with the environment. The overall contrast between the fish and the coral is very low, as its patterns and shapes integrate flawlessly with the complex structure of the sea fan, making it incredibly difficult to distinguish from the background."
}