{
  "entity_type": "Organism",
  "camouflage_presence": "Camouflage",
  "object_category": "Mammal",
  "object_name": "Deer",
  "background_description": "The background depicts a dense deciduous forest environment, likely in late winter or early spring, as trees are mostly bare. There is a cluttered network of thin, leafless branches and twigs dominating the foreground and midground, creating a visual 'noise'. Larger tree trunks with rough, grey-brown bark are visible on the left and in the deeper background. The ground is covered with dry, fallen leaves and some sparse, faded green vegetation. The overall color scheme is muted, featuring various shades of browns, greys, and desaturated greens under soft, diffused lighting.",
  "color_similarity": "high",
  "texture_similarity": "low",
  "contrast_difference": "medium",
  "camouflage_score": "0.75",
  "confidence": "0.9",
  "camouflage_type": "Color blending / Shape disruption",
  "explanation": "The deer demonstrates effective camouflage in this image. Its coat color, a warm grey-brown, closely matches the dominant muted tones of the bare branches, tree trunks, and dry fallen leaves in its environment, contributing to high color similarity. While its fur texture is smooth compared to the rough bark and angular branches (low texture similarity), the most significant camouflage mechanism here is shape disruption. The dense, overlapping network of bare branches in front of and around the deer effectively breaks up its silhouette, making it difficult to discern its complete form. Although the deer's head is somewhat exposed, its body is largely obscured by the branches, reducing its overall contrast against the busy background. The overall effect is that the deer blends well into the visual clutter of the forest."
}