{
  "entity_type": "Organism",
  "camouflage_presence": "Camouflage",
  "object_category": "Arachnid",
  "object_name": "Spider",
  "background_description": "The background consists of a tree trunk covered extensively with vibrant green, small-leaved mosses and lichens, interspersed with areas of darker, rough, brown bark. There are also some small blackish fungal or lichen growths on the bark, creating an uneven and complex texture.",
  "color_similarity": "high",
  "texture_similarity": "high",
  "contrast_difference": "low",
  "camouflage_score": 0.95,
  "confidence": 1.0,
  "camouflage_type": "Pattern matching",
  "explanation": "The spider exhibits exceptional camouflage by perfectly blending with its environment. Its body and legs are intricately patterned with various shades of green, brown, and gray, mirroring the colors of the moss, lichen, and bark. The texture of its exoskeleton is rough and irregular, mimicking the bumpy surface of the moss and the crevices of the tree bark. The complex patterns on its body and limbs effectively break up its outline, making it incredibly difficult to distinguish from the surrounding natural textures and forms. This combination of color matching, texture replication, and pattern disruption results in highly effective concealment."
}