{
  "entity_type": "Organism",
  "camouflage_presence": "No Camouflage",
  "object_category": "Mammal",
  "object_name": "Otters",
  "background_description": "The background consists of clear water with ripples and splashes, bordered by light grey rocks and smaller white/light-colored gravel on the bank. The overall environment appears to be a shallow water area near a rocky shore.",
  "color_similarity": "none",
  "texture_similarity": "none",
  "contrast_difference": "high",
  "camouflage_score": 0.0,
  "confidence": 1.0,
  "camouflage_type": "None",
  "explanation": "The image features two otters playing in water amidst light-colored rocks. While otters possess fur coloration that provides some natural blending in their typical aquatic and semi-aquatic habitats, in this specific bright scene, their dark, wet fur stands out significantly against the lighter grey rocks and clear water. They are highly visible, engaged in a playful interaction, and show no signs of actively trying to blend into their immediate surroundings. There is no active camouflage observed; their natural coloring does not provide effective concealment in this specific context."
}