{
  "entity_type": "Organism",
  "camouflage_presence": "No Camouflage",
  "object_category": "Mammal",
  "object_name": "Red fox",
  "background_description": "The background consists of a winter landscape covered in fresh, white snow, with numerous dry, sparse, brown-grey grass stalks poking through the snow. The ground texture is a mix of soft snow and thin, spiky vegetation.",
  "color_similarity": "low",
  "texture_similarity": "low",
  "contrast_difference": "high",
  "camouflage_score": 0.1,
  "confidence": 0.95,
  "camouflage_type": "None",
  "explanation": "The Red fox's distinct reddish-brown fur creates a high contrast against the predominantly white snowy background. While there are some dull brown grass stalks, they are sparse and do not offer significant concealment. The fox's fur texture is also clearly distinguishable from the snow and dry grass, resulting in low color and texture similarity with its immediate environment. Therefore, the fox is not camouflaged in this snowy setting."
}