{
  "entity_type": "Environment",
  "camouflage_presence": "No Camouflage",
  "object_category": "Environment",
  "object_name": "Seaweed-covered rocky coastline",
  "background_description": "The image captures a vibrant coastal scene featuring an expansive rocky intertidal zone. Numerous rocks, varying in size, are heavily covered with bright green seaweed, creating a textured landscape. Patches of wet, rippled sand and shallow tidal pools reflecting the clear blue sky are interspersed among the rocks. In the background, gentle waves break on the shore, and a verdant, grassy hill slopes upwards under a partly cloudy blue sky.",
  "color_similarity": "none",
  "texture_similarity": "none",
  "contrast_difference": "low",
  "camouflage_score": 0.0,
  "confidence": 1.0,
  "camouflage_type": "None",
  "explanation": "No animal, insect, or fish is visible in the image. The scene exclusively depicts natural environmental elements such as rocks, seaweed, sand, water, and a distant hill. There are no organisms present that exhibit camouflage behavior or features."
}