{
  "entity_type": "Organism",
  "camouflage_presence": "No Camouflage",
  "object_category": "Bird",
  "object_name": "Roseate Spoonbill",
  "background_description": "The background consists primarily of a clear, bright light blue sky. There is a very faint, dark, and highly blurred hint of foliage or land in the bottom right corner, but it does not significantly contribute to the immediate background for the flying bird.",
  "color_similarity": "low",
  "texture_similarity": "low",
  "contrast_difference": "high",
  "camouflage_score": 0.0,
  "confidence": 0.98,
  "camouflage_type": "None",
  "explanation": "The image features a Roseate Spoonbill in flight against a clear blue sky. The bird's prominent pink and white plumage creates a high contrast against the uniform light blue background, making it easily visible. Roseate Spoonbills are known for their distinctive vibrant coloration, which is typically used for display rather than concealment. There is no indication of color blending, disruptive patterns, or mimicry applied to hide the bird in this open sky environment. Therefore, no camouflage is present."
}