{
  "entity_type": "Organism",
  "camouflage_presence": "Camouflage",
  "object_category": "Insect",
  "object_name": "Mantis",
  "background_description": "The background consists of a dense array of thin, vertical plant stalks and blades of grass. Many of these stalks are green and vibrant, while others, particularly in the foreground where the mantis is situated, appear dried, brittle, and brownish-tan. There are also small, round seed pods on some of the stalks, and a blurred, distant light green foliage, with a faint purple flower in the lower mid-background.",
  "color_similarity": "medium",
  "texture_similarity": "high",
  "contrast_difference": "medium",
  "camouflage_score": "0.75",
  "confidence": "0.95",
  "camouflage_type": "Mimicry",
  "explanation": "The Mantis exhibits strong camouflage primarily through mimicry. Its elongated, slender body is a brownish-tan color, which closely matches the dried and senescent plant stalks it is clinging to in the foreground. The texture of its body, with its segmented appearance, also blends well with the rough, linear textures of the surrounding twigs and stems. While the overall background has a significant amount of vibrant green, the mantis strategically positions itself among the brown, dead, or drying vegetation, where its stick-like form is highly effective at blending in. Its posture further enhances this mimicry, making it appear like just another dried stem rather than an insect."
}